<?xml version="1.0" encoding="UTF-8"?>
<!--
  #%L
  xplan-workspaces - Modul zur Gruppierung aller Workspaces
  %%
  Copyright (C) 2008 - 2022 lat/lon GmbH, info@lat-lon.de, www.lat-lon.de
  %%
  This program is free software: you can redistribute it and/or modify
  it under the terms of the GNU Affero General Public License as published by
  the Free Software Foundation, either version 3 of the License, or
  (at your option) any later version.
  
  This program is distributed in the hope that it will be useful,
  but WITHOUT ANY WARRANTY; without even the implied warranty of
  MERCHANTABILITY or FITNESS FOR A PARTICULAR PURPOSE.  See the
  GNU General Public License for more details.
  
  You should have received a copy of the GNU Affero General Public License
  along with this program.  If not, see <http://www.gnu.org/licenses/>.
  #L%
  -->

<FeatureTypeStyle xmlns="http://www.opengis.net/se" xmlns:ogc="http://www.opengis.net/ogc"
  xmlns:xplan="http://www.deegree.org/xplanung/1/0"
  xmlns:xsi="http://www.w3.org/2001/XMLSchema-instance"
  xsi:schemaLocation="http://www.opengis.net/se http://schemas.opengis.net/se/1.1.0/FeatureStyle.xsd">
  <Name>vollflaechig</Name>
  <FeatureTypeName>xplan:XP_LTO</FeatureTypeName>
  <Rule>
    <Name>so_xp_lto</Name>
    <Description>
      <Title>SO: Beschriftung</Title>
    </Description>
    <ogc:Filter>
      <ogc:And>
        <ogc:Not>
          <ogc:PropertyIsNull>
            <ogc:PropertyName>xplan:schriftinhalt</ogc:PropertyName>
          </ogc:PropertyIsNull>
        </ogc:Not>
        <ogc:PropertyIsEqualTo>
          <ogc:PropertyName>xplan:xpPlanType</ogc:PropertyName>
          <ogc:Literal>SO_Plan</ogc:Literal>
        </ogc:PropertyIsEqualTo>
      </ogc:And>
    </ogc:Filter>
    <TextSymbolizer uom="meter">
      <Geometry>
        <ogc:PropertyName>xplan:position</ogc:PropertyName>
      </Geometry>
      <Label>
        <ogc:PropertyName>xplan:schriftinhalt</ogc:PropertyName>
      </Label>
      <Font>
        <SvgParameter name="font-family">Arial</SvgParameter>
        <SvgParameter name="font-family">Sans-Serif</SvgParameter>
        <SvgParameter name="font-weight">bold</SvgParameter>
        <SvgParameter name="font-size">3</SvgParameter>
      </Font>
      <LabelPlacement>
        <LinePlacement>
          <IsRepeated>false</IsRepeated>
          <IsAligned>true</IsAligned>
        </LinePlacement>
      </LabelPlacement>
      <Halo>
        <Radius>0.3</Radius>
        <Fill>
          <SvgParameter name="fill">#ffffff</SvgParameter>
          <SvgParameter name="fill-opacity">0.8</SvgParameter>
        </Fill>
      </Halo>
      <Fill>
        <SvgParameter name="fill">#000000</SvgParameter>
      </Fill>
    </TextSymbolizer>
  </Rule>
</FeatureTypeStyle>
